{"DGEDwQwPOI2gcOrII1q9Kg==":"fondo-transparente-1772x709.png","UG8VQUasZqZ+hCIPMRUwAA==":"unrecognizable-businesswoman-with-tablet-working-p9ljy5y-1999x1333.jpg","vw+G4RLRHZi4KFn72DIaQA==":"senior-businessman-working-on-tablet-in-cafe-prrjqz5-2000x1333.jpg","/ggpc4jLCj7GUHBtqGqACw==":"businessman-holding-money-in-his-hands-prbs4f3-2000x1333.jpg","EAqNYCk5xNUTYZP7jpQBww==":"business-meeting-young-hipsters-businessmen-and-pucaqe3-2000x1333.jpg","wwo8Oz4yJ4PYc/zwTKXLuw==":"equimera_aviso_app-1200x628.png","jXRHQ/fwDzdng4g52COCfg==":"trazabilidad1-547x374.jpg","Y3p0sClGHByhCLkBlzCZ1A==":"venta01-800x531.jpg","Ziywm0BlkxxVg11QzhbcRg==":"mbr-1626x1080.jpg","mc0vre96bBylC6V1SAwZyg==":"mbr-1618x1080.jpg","Ay4E5wTVgi/odyD3mS6ekw==":"equimera_app_negocio1-590x1131.png","8r3Pg1TqhKwMsLVLjKg/Mw==":"equimera_aviso_app-1-1200x628.png","z1X4yavJUWSqIfsQOlPb2Q==":"equimera_aviso_app-2-1200x628.png","39V+E6SlAynkkYQiWWnQow==":"equimera_aviso_app-3-1200x628.png","I5uW0HZCudB8GrqevKdtpQ==":"mbr-719x1080.jpg","88sfj9OZThQk11EzFvNL4w==":"logo_solo_1_color-413x236.png","uzv63MkOP0vtyOWQcxAW4Q==":"logo_solo_1_color-1-413x236.png","ZAgq6ASaU4Sx0GsHnR/U8g==":"pfizer-300x300.png","5W43fWpxITnbsj0BGS/e1Q==":"mbr-1620x1080.jpg","JECHQPDiUW4lT+5CGfOJUA==":"mbr-1-1620x1080.jpg","mzS/903A922MXUDg6/3q+w==":"mbr-1-1626x1080.jpg"}